{
  "project_info": {
    "project_number": "899017442870",
    "project_id": "yummy-app-f2567",
    "storage_bucket": "yummy-app-f2567.appspot.com"
  },
  "client": [
    {
      "client_info": {
        "mobilesdk_app_id": "1:899017442870:android:1bd7fa481303ba97b5ba97",
        "android_client_info": {
          "package_name": "eg.gov.iti.yummy"
        }
      },
      "oauth_client": [
        {
          "client_id": "899017442870-i9jkm8negvqr8d9cekvhudcuotilsqjs.apps.googleusercontent.com",
          "client_type": 1,
          "android_info": {
            "package_name": "eg.gov.iti.yummy",
            "certificate_hash": "8db4ea3c74a3af0e977c22e27eaa9b826a46350f"
          }
        },
        {
          "client_id": "899017442870-f9qagfcr0vbuetuirffe8vuh4pl2tm1h.apps.googleusercontent.com",
          "client_type": 3
        }
      ],
      "api_key": [
        {
          "current_key": "AIzaSyBI9w1ArsgV6gOEpNaGnooVKu8GDXsIlN8"
        }
      ],
      "services": {
        "appinvite_service": {
          "other_platform_oauth_client": [
            {
              "client_id": "899017442870-f9qagfcr0vbuetuirffe8vuh4pl2tm1h.apps.googleusercontent.com",
              "client_type": 3
            }
          ]
        }
      }
    }
  ],
  "configuration_version": "1"
}